sythonlab_airport_docs/__init__.py
sythonlab_airport_docs/api.py
sythonlab_airport_docs/normalize.py
sythonlab_airport_docs/pnl.py
sythonlab_airport_docs/entities/__init__.py
sythonlab_airport_docs/entities/contact_info.py
sythonlab_airport_docs/entities/flight.py
sythonlab_airport_docs/entities/pax.py
sythonlab_airport_docs-0.1.2.dist-info/METADATA
sythonlab_airport_docs-0.1.2.dist-info/WHEEL
sythonlab_airport_docs-0.1.2.dist-info/top_level.txt
sythonlab_airport_docs-0.1.2.dist-info/RECORD
