Metadata-Version: 2.4
Name: sythonlab_airport_docs
Version: 0.1.2
Summary: Generation of documentation and mandatory reports required by airports and customs for travel, including Passenger Name Lists (PNL) for airline check-in systems..
Home-page: https://github.com/sythonlab/SythonLab-Airport-Docs
Author: José Angel Alvarez Abraira
Author-email: sythonlab@gmail.com
Classifier: Development Status :: 3 - Alpha
Classifier: Intended Audience :: Developers
Classifier: Programming Language :: Python :: 3
Classifier: Programming Language :: Python :: 3.7
Classifier: Programming Language :: Python :: 3.8
Classifier: Programming Language :: Python :: 3.9
Dynamic: author
Dynamic: author-email
Dynamic: classifier
Dynamic: description-content-type
Dynamic: home-page
Dynamic: summary
